hnget/__init__.py
hnget/application.py
hnget-0.1.91.dist-info/entry_points.txt
hnget-0.1.91.dist-info/LICENSE
hnget-0.1.91.dist-info/WHEEL
hnget-0.1.91.dist-info/METADATA
hnget-0.1.91.dist-info/RECORD
