Metadata-Version: 2.1
Name: hnget
Version: 0.1.91
Summary: Shows and opens links on Hacker news from the terminal
Author: Jordan Sweet
Author-email: hello@jordandsweet.com
Requires-Python: >=3.8,<4.0
Classifier: Programming Language :: Python :: 3
Classifier: Programming Language :: Python :: 3.10
Classifier: Programming Language :: Python :: 3.8
Classifier: Programming Language :: Python :: 3.9
Requires-Dist: lxml (>=4.6.3,<5.0.0)
Requires-Dist: requests (>=2.26.0,<3.0.0)
